xia_cloudmailin/__init__.py
xia_cloudmailin/mail.cp310-win_amd64.pyd
xia_cloudmailin-0.0.10.dist-info/LICENSE.txt
xia_cloudmailin-0.0.10.dist-info/METADATA
xia_cloudmailin-0.0.10.dist-info/WHEEL
xia_cloudmailin-0.0.10.dist-info/top_level.txt
xia_cloudmailin-0.0.10.dist-info/RECORD
