Metadata-Version: 2.1
Name: xia-cloudmailin
Version: 0.0.10
Home-page: https://develop.x-i-a.com/docs/xia-cloudmailin/0.0.10/index.html
Author: X-I-A
Author-email: admin@x-i-a.com
Requires-Python: >=3.9
License-File: LICENSE.txt
Requires-Dist: xia-mail
